aurapy-2.9.0.dist-info/METADATA
aurapy-2.9.0.dist-info/WHEEL
aurapy-2.9.0.dist-info/top_level.txt
aurapy-2.9.0.dist-info/RECORD
aurapy/__main__.py
aurapy/timer.py
aurapy/demo.py
aurapy/console_gw.py
aurapy/connection.py
aurapy/auraclient.py
aurapy/sim_demo.py
aurapy/_aura_pybind.cpython-310-x86_64-linux-gnu.so
aurapy/units.py
aurapy/dialog_utils.py
aurapy/console_mc.py
aurapy/console.py
aurapy/aurahub.py
aurapy/console_common.py
aurapy/selector.py
aurapy/libMU_3SL_interface.so.3
aurapy/conf_updater.py
aurapy/show_encoder_calib.py
aurapy/mock.py
aurapy/flashage.py
aurapy/__init__.py
aurapy/binaries/aura_mc-2023.2.9-f446-ihm07.update
aurapy/binaries/aura_mc-2023.3.0-h725-aura.v0.7_A_7mO5.update
aurapy/binaries/aura_mc-2023.2.9-h725-aura.v0.7_A_7mO5.update
aurapy/binaries/aura_mc-2023.2.9-h725-aura.v0.7_A_20mO.update
aurapy/binaries/aura_mc-2023.2.10-h725-aura.v0.6_B_A1.update
aurapy/binaries/aura_mc-2023.2.10-g474-aura.update
aurapy/binaries/aura_mc-2023.3.0-g474-aura.update
aurapy/binaries/aura_mc-2023.2.9-h725-aura.v0.6_B_A1.update
aurapy/binaries/aura_mc-2023.3.0-f446-ihm07_144.update
aurapy/binaries/aura_mc-2023.2.9-h725-aura.v0.7_A_2mO5.update
aurapy/binaries/aura_gateway-2023.2.9-h723-core.v1.1_A.update
aurapy/binaries/aura_mc-2023.3.0-f446-ihm08.update
aurapy/binaries/aura_mc-2023.2.9-h725-aura.v0.7_A_4mO.update
aurapy/binaries/aura_gateway-2023.2.10-g474-fdcanusb.update
aurapy/binaries/aura_mc-2023.2.10-f446-ihm07.update
aurapy/binaries/aura_gateway-2023.3.0-h723-core.v1.1_A.update
aurapy/binaries/aura_gateway-2023.2.9-g474-fdcanusb.update
aurapy/binaries/aura_mc-2023.3.0-h725-aura.v0.8_A_20mO.update
aurapy/binaries/aura_gateway-2023.2.10-h723-core.v1.1_A.update
aurapy/binaries/aura_mc-2023.2.10-h725-aura.v0.7_A_20mO.update
aurapy/binaries/aura_mc-2023.2.9-h725-aura.v0.6_B_A2.update
aurapy/binaries/aura_mc-2023.2.10-h725-aura.v0.7_A_4mO.update
aurapy/binaries/aura_mc-2023.3.0-h725-aura.v0.7_A_4mO.update
aurapy/binaries/aura_mc-2023.3.0-f446-ihm07.update
aurapy/binaries/aura_mc-2023.3.0-h725-aura.v0.8_A_4mO.update
